influence_api/__init__.py
influence_api/client.py
influence_api/constants.py
influence_api/tests.py
influence_api/util.py
influence_api-0.2.2.dist-info/LICENSE
influence_api-0.2.2.dist-info/METADATA
influence_api-0.2.2.dist-info/WHEEL
influence_api-0.2.2.dist-info/top_level.txt
influence_api-0.2.2.dist-info/RECORD
