Metadata-Version: 2.1
Name: influence-api
Version: 0.2.2
Summary: An API for Influence (influenceth.io)
Home-page: https://gitlab.com/gamechaingers/influence-api
Author: GameChaingers, LLC
Author-email: engineering@gamechaingers.io
License: OSI Approved :: BSD License
Platform: UNKNOWN
Classifier: Programming Language :: Python :: 3
Classifier: Programming Language :: Python :: 3.7
Classifier: Programming Language :: Python :: 3.8
Classifier: Programming Language :: Python :: 3.9
Classifier: Programming Language :: Python :: 3.10
Classifier: Development Status :: 2 - Pre-Alpha
Classifier: Intended Audience :: Developers
Classifier: License :: OSI Approved :: BSD License
Classifier: Operating System :: OS Independent
Classifier: Topic :: Software Development :: Libraries
Requires-Python: >=3.7
License-File: LICENSE
Requires-Dist: requests
Requires-Dist: requests-cache
Requires-Dist: requests-oauthlib
